pysfmc/__init__.py
pysfmc/auth.py
pysfmc/client.py
pysfmc/config.py
pysfmc/exceptions.py
pysfmc/assets/__init__.py
pysfmc/assets/categories.py
pysfmc/assets/client.py
pysfmc/assets/content.py
pysfmc/assets/query.py
pysfmc/models/__init__.py
pysfmc/models/base.py
pysfmc/models/assets/__init__.py
pysfmc/models/assets/asset_types.py
pysfmc/models/assets/assets.py
pysfmc/models/assets/block_types.py
pysfmc/models/assets/blocks.py
pysfmc/models/assets/categories.py
pysfmc/models/assets/views.py
pysfmc-0.1.4.dist-info/METADATA
pysfmc-0.1.4.dist-info/WHEEL
pysfmc-0.1.4.dist-info/licenses/LICENSE
pysfmc-0.1.4.dist-info/RECORD
