Metadata-Version: 2.4
Name: pysfmc
Version: 0.1.4
Summary: Python client for Salesforce Marketing Cloud (SFMC) API
Project-URL: Repository, https://github.com/dardT/pysfmc
Project-URL: Homepage, https://github.com/dardT/pysfmc
License-File: LICENSE
Requires-Python: >=3.10
Requires-Dist: httpx>=0.25.0
Requires-Dist: pydantic-settings>=2.0.0
Requires-Dist: pydantic>=2.0.0
